{
  "ticker": "afcom-holdings",
  "name": "Afcom Holdings",
  "exchange": "",
  "sector": "",
  "generatedAt": "2026-07-24T04:45:20.246Z",
  "posts": [
    {
      "id": "valuepickr-645855",
      "source": "valuepickr",
      "author": "radhakishandamani",
      "handle": "@radhakishandamani",
      "community": "Afcom Holdings - Sky High Ambitions, Grounded in Reality?",
      "timestamp": "2026-07-06T14:24:34.925Z",
      "text": "20260706_152340 1920×2400 910 KB x.com Afcom Cargo (@AfcomCargo) on X @AfcomCargo ✈️ The Next Chapter in Air Cargo Excellence. AFCOM Cargo proudly launches its new Mumbai (BOM) ↔ Dubai World Central (DWC) Air Cargo Corridor. 📅 Inaugural Flight: 10 July 2026 🔄 Twice Weekly Operations (Day 3 & Day 5) #AFCOMCargo #AirCargo #Logistics #IndiaUAE #GlobalTrade",
      "url": "https://forum.valuepickr.com/t/afcom-holdings-sky-high-ambitions-grounded-in-reality/214074/100",
      "sentiment": "neutral",
      "likes": 4,
      "comments": 0
    },
    {
      "id": "valuepickr-645562",
      "source": "valuepickr",
      "author": "radhakishandamani",
      "handle": "@radhakishandamani",
      "community": "Afcom Holdings - Sky High Ambitions, Grounded in Reality?",
      "timestamp": "2026-07-03T10:08:31.468Z",
      "text": "3rd Plane VT-AFJ has started showing up on flightradar24 now. But VT-AFN has been grounded for about a month.",
      "url": "https://forum.valuepickr.com/t/afcom-holdings-sky-high-ambitions-grounded-in-reality/214074/99",
      "sentiment": "neutral",
      "likes": 3,
      "comments": 0
    }
  ]
}
