{
  "ticker": "pngs-gargi-fashion-jewellery",
  "name": "PNGS Gargi Fashion Jewellery",
  "exchange": "",
  "sector": "",
  "generatedAt": "2026-05-29T16:56:39.658Z",
  "posts": [
    {
      "id": "valuepickr-640339",
      "source": "valuepickr",
      "author": "Marathondreams",
      "handle": "@Marathondreams",
      "community": "PNGS Gargi Fashion Jewellery Ltd",
      "timestamp": "2026-05-07T08:17:25.883Z",
      "text": "Company hired investor relations firm and it must have helped them preparing their first ever investor presentation . It seems IR firm also influenced company to conduct conference call on the day of results. Such investor friendly steps would help company get better known in the investor community. In-spite of giving stellar results (BTW their IR firms name is Stellar.. ) for last few quarters, stock continues to languish only due to its SME tag. Hopefully that will go away in Q3 FY 27 as they will be able to fulfill mainboard listing condition. Disclosure - Major PF contributor. Continues to…",
      "url": "https://forum.valuepickr.com/t/pngs-gargi-fashion-jewellery-ltd/107967/122",
      "sentiment": "neutral",
      "likes": 7,
      "comments": 0
    },
    {
      "id": "valuepickr-640261",
      "source": "valuepickr",
      "author": "sanketkulkarni1987",
      "handle": "@sanketkulkarni1987",
      "community": "PNGS Gargi Fashion Jewellery Ltd",
      "timestamp": "2026-05-06T10:09:45.940Z",
      "text": "Good Q4 performance with positive commentary for next 2 years. With market tailwinds and low branded penetration, the opportunity in this space is immense. Efforts towards brand building can lead to exponential results in the years to come. Promoters have so far walked the talk and seem to be fair and transparent. The PNG name has a strong pull in Maharashtra. What remains to be seen is how they leverage the 190 year old brand name to scale newer and greater heights Disc: Invested",
      "url": "https://forum.valuepickr.com/t/pngs-gargi-fashion-jewellery-ltd/107967/121",
      "sentiment": "neutral",
      "likes": 6,
      "comments": 0
    },
    {
      "id": "valuepickr-640256",
      "source": "valuepickr",
      "author": "satishwe",
      "handle": "@satishwe",
      "community": "PNGS Gargi Fashion Jewellery Ltd",
      "timestamp": "2026-05-06T09:32:31.169Z",
      "text": "cad5001c-f410-4721-b743-22ae1f6fb865.pdf (3.2 MB) First ever PPT from Gargi !",
      "url": "https://forum.valuepickr.com/t/pngs-gargi-fashion-jewellery-ltd/107967/120",
      "sentiment": "neutral",
      "likes": 5,
      "comments": 0
    }
  ]
}
